{
  "total_score": 5,
  "max_possible_score": 27,
  "responses": {
    "ANHEDONIA": {
      "Dalam 2 minggu terakhir apakah Anda merasa kurang tertarik atau bergairah dalam melakukan apapun?": {
        "response_text": "Tidak sama sekali",
        "response_value": 0,
        "response_time_ms": 9422,
        "timing": {
          "start": 0,
          "end": 9,
          "duration": 9
        }
      }
    },
    "DEPRESSED_MOOD": {
      "Dalam 2 minggu terakhir apakah Anda merasa murung, muram, atau putus asa?": {
        "response_text": "Tidak sama sekali",
        "response_value": 0,
        "response_time_ms": 7803,
        "timing": {
          "start": 17,
          "end": 25,
          "duration": 8
        }
      }
    },
    "SLEEP_DISTURBANCE": {
      "Selama 2 minggu terakhir, apakah Anda mengalami kesulitan untuk tidur nyenyak, sering terbangun di malam hari, atau justru tidur berlebihan?": {
        "response_text": "Pernah (jarang)",
        "response_value": 1,
        "response_time_ms": 5528,
        "timing": {
          "start": 26,
          "end": 31,
          "duration": 5
        }
      }
    },
    "FATIGUE": {
      "Dalam rentang 2 minggu terakhir, apakah tubuh Anda sering terasa lelah atau tidak berenergi?": {
        "response_text": "Beberapa kali (cukup sering)",
        "response_value": 2,
        "response_time_ms": 4964,
        "timing": {
          "start": 33,
          "end": 38,
          "duration": 5
        }
      }
    },
    "APPETITE_CHANGES": {
      "Dalam 2 minggu terakhir apakah Anda merasa kurang nafsu makan atau terlalu banyak makan?": {
        "response_text": "Tidak sama sekali",
        "response_value": 0,
        "response_time_ms": 2816,
        "timing": {
          "start": 39,
          "end": 42,
          "duration": 3
        }
      }
    },
    "WORTHLESSNESS": {
      "Dalam rentang 2 minggu terakhir, apakah muncul perasaan rendah diri, keyakinan bahwa Anda gagal, atau pikiran telah mengecewakan diri sendiri serta keluarga?": {
        "response_text": "Pernah (jarang)",
        "response_value": 1,
        "response_time_ms": 5272,
        "timing": {
          "start": 44,
          "end": 50,
          "duration": 6
        }
      }
    },
    "CONCENTRATION": {
      "Selama 2 minggu terakhir, adakah Anda mengalami kesulitan untuk memusatkan perhatian pada kegiatan, misalnya membaca berita atau menonton tayangan media?": {
        "response_text": "Pernah (jarang)",
        "response_value": 1,
        "response_time_ms": 8508,
        "timing": {
          "start": 51,
          "end": 60,
          "duration": 9
        }
      }
    },
    "PSYCHOMOTOR": {
      "Dalam 2 minggu terakhir apakah Anda merasa bergerak atau berbicara sangat lambat sehingga orang lain memperhatikannya. Atau sebaliknya merasa resah atau gelisah sehingga Anda lebih sering bergerak dari biasanya?": {
        "response_text": "Tidak sama sekali",
        "response_value": 0,
        "response_time_ms": 4598,
        "timing": {
          "start": 61,
          "end": 65,
          "duration": 4
        }
      }
    },
    "SUICIDAL_IDEATION": {
      "Dalam 2 minggu terakhir apakah Anda merasa lebih baik mati atau ingin melukai diri sendiri dengan cara apapun?": {
        "response_text": "Tidak sama sekali",
        "response_value": 0,
        "response_time_ms": 4416,
        "timing": {
          "start": 67,
          "end": 71,
          "duration": 4
        }
      }
    }
  }
}