{
  "total_score": 9,
  "max_possible_score": 27,
  "responses": {
    "ANHEDONIA": {
      "Selama 2 minggu terakhir, Anda merasa kehilangan minat atau tidak bersemangat untuk melakukan kegiatan apa pun?": {
        "response_text": "Beberapa kali (cukup sering)",
        "response_value": 2,
        "response_time_ms": 6453,
        "timing": {
          "start": 0,
          "end": 6,
          "duration": 6
        }
      }
    },
    "DEPRESSED_MOOD": {
      "Dalam rentang 2 minggu terakhir, apakah muncul perasaan murung, muram, ataupun putus asa pada diri Anda?": {
        "response_text": "Pernah (jarang)",
        "response_value": 1,
        "response_time_ms": 4024,
        "timing": {
          "start": 8,
          "end": 12,
          "duration": 4
        }
      }
    },
    "SLEEP_DISTURBANCE": {
      "Dalam rentang 2 minggu terakhir, adakah gangguan tidur seperti sulit memulai tidur, mudah terbangun, ataupun tidur terlalu lama?": {
        "response_text": "Beberapa kali (cukup sering)",
        "response_value": 2,
        "response_time_ms": 4041,
        "timing": {
          "start": 13,
          "end": 17,
          "duration": 4
        }
      }
    },
    "FATIGUE": {
      "Selama 2 minggu terakhir, adakah Anda kerap merasa letih atau kehilangan tenaga?": {
        "response_text": "Pernah (jarang)",
        "response_value": 1,
        "response_time_ms": 3993,
        "timing": {
          "start": 17,
          "end": 21,
          "duration": 4
        }
      }
    },
    "APPETITE_CHANGES": {
      "Selama 2 minggu terakhir, adakah perubahan pada selera makan Anda, seperti berkurang drastis atau justru berlebihan?": {
        "response_text": "Tidak sama sekali",
        "response_value": 0,
        "response_time_ms": 2209,
        "timing": {
          "start": 22,
          "end": 24,
          "duration": 2
        }
      }
    },
    "WORTHLESSNESS": {
      "Dalam 2 minggu terakhir apakah Anda merasa kurang percaya diri, atau merasa bahwa Anda adalah orang yang gagal atau telah mengecewakan diri sendiri atau keluarga?": {
        "response_text": "Pernah (jarang)",
        "response_value": 1,
        "response_time_ms": 2919,
        "timing": {
          "start": 25,
          "end": 27,
          "duration": 2
        }
      }
    },
    "CONCENTRATION": {
      "Dalam rentang 2 minggu terakhir, apakah Anda merasa konsentrasi Anda mudah buyar ketika melakukan sesuatu seperti membaca berita atau menonton tayangan media?": {
        "response_text": "Beberapa kali (cukup sering)",
        "response_value": 2,
        "response_time_ms": 3407,
        "timing": {
          "start": 28,
          "end": 32,
          "duration": 4
        }
      }
    },
    "PSYCHOMOTOR": {
      "Dalam rentang 2 minggu terakhir, apakah Anda mengalami perubahan seperti bergerak atau berbicara jauh lebih lambat, atau justru merasa resah sehingga aktivitas tubuh Anda meningkat?": {
        "response_text": "Tidak sama sekali",
        "response_value": 0,
        "response_time_ms": 2940,
        "timing": {
          "start": 32,
          "end": 35,
          "duration": 3
        }
      }
    },
    "SUICIDAL_IDEATION": {
      "Dalam rentang 2 minggu terakhir, apakah Anda mengalami dorongan atau pikiran tentang kematian, atau tentang melukai diri sendiri?": {
        "response_text": "Tidak sama sekali",
        "response_value": 0,
        "response_time_ms": 3487,
        "timing": {
          "start": 36,
          "end": 39,
          "duration": 3
        }
      }
    }
  }
}